fattureincloud/__init__.py
fattureincloud/client.py
fattureincloud/exceptions.py
fattureincloud/models/__init__.py
fattureincloud/models/acquisti.py
fattureincloud/models/anagrafica.py
fattureincloud/models/base.py
fattureincloud/models/corrispettivi.py
fattureincloud/models/documenti.py
fattureincloud/models/magazzino.py
fattureincloud/models/mail.py
fattureincloud/models/prodotti.py
python_fattureincloud-0.0.1.dist-info/LICENSE.md
python_fattureincloud-0.0.1.dist-info/METADATA
python_fattureincloud-0.0.1.dist-info/WHEEL
python_fattureincloud-0.0.1.dist-info/top_level.txt
python_fattureincloud-0.0.1.dist-info/RECORD
