Metadata-Version: 2.1
Name: python-fattureincloud
Version: 0.0.1
Summary: A python wrapper for FattureInCloud REST API
Home-page: https://github.com/20tab/python-fattureincloud
Author: 20tab srl
Author-email: info@20tab.com
License: UNKNOWN
Project-URL: Bug Tracker, https://github.com/20tab/python-fattureincloud/issues
Platform: UNKNOWN
Classifier: Programming Language :: Python :: 3
Classifier: License :: OSI Approved :: MIT License
Classifier: Operating System :: OS Independent
Requires-Python: >=3.7
